PythonVisualizer/__init__.py
PythonVisualizer/api.py
PythonVisualizer/core/__init__.py
PythonVisualizer/core/executor.py
PythonVisualizer/core/parser.py
PythonVisualizer/core/tracer.py
PythonVisualizer/utils/__init__.py
PythonVisualizer/utils/serializer.py
PythonVisualizer/visualization/__init__.py
PythonVisualizer/visualization/web_renderer.py
PythonVisualizer/visualization/templates/view.html.j2
python_code_visualizer-1.0.2.dist-info/licenses/LICENSE
python_code_visualizer-1.0.2.dist-info/METADATA
python_code_visualizer-1.0.2.dist-info/WHEEL
python_code_visualizer-1.0.2.dist-info/top_level.txt
python_code_visualizer-1.0.2.dist-info/RECORD
