Metadata-Version: 2.4
Name: python-code-visualizer
Version: 1.0.2
Summary: An interactive step-by-step Python code execution visualizer
Author-email: Jayachandran P M <jayachandranpm2001@gmail.com>
Maintainer-email: Jayachandran P M <jayachandranpm2001@gmail.com>
License: MIT
Project-URL: Homepage, https://github.com/jayachandranpm/python-code-visualizer
Project-URL: Documentation, https://github.com/jayachandranpm/python-code-visualizer#readme
Project-URL: Repository, https://github.com/jayachandranpm/python-code-visualizer.git
Project-URL: Issues, https://github.com/jayachandranpm/python-code-visualizer/issues
Project-URL: Changelog, https://github.com/jayachandranpm/python-code-visualizer/releases
Keywords: python,visualizer,debugger,education,code-execution,step-by-step,trace,learning
Classifier: Development Status :: 5 - Production/Stable
Classifier: Intended Audience :: Developers
Classifier: Intended Audience :: Education
Classifier: License :: OSI Approved :: MIT License
Classifier: Operating System :: OS Independent
Classifier: Programming Language :: Python :: 3
Classifier: Programming Language :: Python :: 3.8
Classifier: Programming Language :: Python :: 3.9
Classifier: Programming Language :: Python :: 3.10
Classifier: Programming Language :: Python :: 3.11
Classifier: Programming Language :: Python :: 3.12
Classifier: Topic :: Education
Classifier: Topic :: Software Development :: Debuggers
Classifier: Topic :: Software Development :: Libraries :: Python Modules
Requires-Python: >=3.8
License-File: LICENSE
Requires-Dist: jinja2>=3.0.0
Provides-Extra: dev
Requires-Dist: pytest>=7.0.0; extra == "dev"
Requires-Dist: pytest-cov>=4.0.0; extra == "dev"
Requires-Dist: black>=23.0.0; extra == "dev"
Requires-Dist: isort>=5.0.0; extra == "dev"
Requires-Dist: flake8>=6.0.0; extra == "dev"
Dynamic: license-file
